matplotlib_terminal/__init__.py
matplotlib_terminal/backend.py
matplotlib_terminal-0.1a4.dist-info/LICENSE
matplotlib_terminal-0.1a4.dist-info/METADATA
matplotlib_terminal-0.1a4.dist-info/WHEEL
matplotlib_terminal-0.1a4.dist-info/top_level.txt
matplotlib_terminal-0.1a4.dist-info/RECORD
