Metadata-Version: 2.1
Name: matplotlib-terminal
Version: 0.1a4
Summary: Render matplotlib plots in terminal.
Home-page: https://github.com/matrach/matplotlib-terminal
Author: Maciej Matraszek
Author-email: matraszek.maciej@gmail.com
License: MIT
Platform: UNKNOWN
Classifier: Programming Language :: Python :: 3
Classifier: License :: OSI Approved :: MIT License
Classifier: Operating System :: OS Independent
Requires-Python: >=3.6
Provides-Extra: develop
